goodtogo/__init__.py
goodtogo/cli.py
goodtogo/container.py
goodtogo/adapters/__init__.py
goodtogo/adapters/agent_state.py
goodtogo/adapters/cache_memory.py
goodtogo/adapters/cache_sqlite.py
goodtogo/adapters/github.py
goodtogo/adapters/time_provider.py
goodtogo/core/__init__.py
goodtogo/core/analyzer.py
goodtogo/core/errors.py
goodtogo/core/interfaces.py
goodtogo/core/models.py
goodtogo/core/validation.py
goodtogo/parsers/__init__.py
goodtogo/parsers/claude.py
goodtogo/parsers/coderabbit.py
goodtogo/parsers/cursor.py
goodtogo/parsers/generic.py
goodtogo/parsers/greptile.py
gtg-0.8.0.dist-info/licenses/LICENSE
gtg-0.8.0.dist-info/METADATA
gtg-0.8.0.dist-info/WHEEL
gtg-0.8.0.dist-info/entry_points.txt
gtg-0.8.0.dist-info/top_level.txt
gtg-0.8.0.dist-info/RECORD
